[
  {
    "Name": "Methane",
    "Type": "Gas",
    "Formula": "CH4",
    "Symbol": "CH₄",
    "MolarMass": 16.04,
    "C": 1,
    "H": 4,
    "O": 0,
    "N": 0,
    "S": 0,
    "AshContent": 0,
    "MoistureContent": 0,
    "HeatingValue": 50.00,
    "HHV": 55.50
  },
  {
    "Name": "Ethane",
    "Type": "Gas",
    "Formula": "C2H6",
    "Symbol": "C₂H₆",
    "MolarMass": 30.07,
    "C": 2,
    "H": 6,
    "O": 0,
    "N": 0,
    "S": 0,
    "AshContent": 0,
    "MoistureContent": 0,
    "HeatingValue": 47.50,
    "HHV": 51.90
  },
  {
    "Name": "Propane",
    "Type": "Gas",
    "Formula": "C3H8",
    "Symbol": "C₃H₈",
    "MolarMass": 44.09,
    "C": 3,
    "H": 8,
    "O": 0,
    "N": 0,
    "S": 0,
    "AshContent": 0,
    "MoistureContent": 0,
    "HeatingValue": 46.35,
    "HHV": 50.35
  },
  {
    "Name": "Butane",
    "Type": "Gas",
    "Formula": "C4H10",
    "Symbol": "C₄H₁₀",
    "MolarMass": 58.12,
    "C": 4,
    "H": 10,
    "O": 0,
    "N": 0,
    "S": 0,
    "AshContent": 0,
    "MoistureContent": 0,
    "HeatingValue": 45.75,
    "HHV": 49.75
  },
  {
    "Name": "Pentane",
    "Type": "Gas",
    "Formula": "C5H12",
    "Symbol": "C₅H₁₂",
    "MolarMass": 72.15,
    "C": 5,
    "H": 12,
    "O": 0,
    "N": 0,
    "S": 0,
    "AshContent": 0,
    "MoistureContent": 0,
    "HeatingValue": 45.00,
    "HHV": 48.90
  },
  {
    "Name": "Hexane",
    "Type": "Gas",
    "Formula": "C6H14",
    "Symbol": "C₆H₁₄",
    "MolarMass": 86.18,
    "C": 6,
    "H": 14,
    "O": 0,
    "N": 0,
    "S": 0,
    "AshContent": 0,
    "MoistureContent": 0,
    "HeatingValue": 44.25,
    "HHV": 48.00
  },
  {
    "Name": "Heptane",
    "Type": "Gas",
    "Formula": "C7H16",
    "Symbol": "C₇H₁₆",
    "MolarMass": 100.21,
    "C": 7,
    "H": 16,
    "O": 0,
    "N": 0,
    "S": 0,
    "AshContent": 0,
    "MoistureContent": 0,
    "HeatingValue": 43.50,
    "HHV": 47.70
  },
  {
    "Name": "Octane",
    "Type": "Gas",
    "Formula": "C8H18",
    "Symbol": "C₈H₁₈",
    "MolarMass": 114.23,
    "C": 8,
    "H": 18,
    "O": 0,
    "N": 0,
    "S": 0,
    "AshContent": 0,
    "MoistureContent": 0,
    "HeatingValue": 42.75,
    "HHV": 47.40
  },
  {
    "Name": "Nonane",
    "Type": "Gas",
    "Formula": "C9H20",
    "Symbol": "C₉H₂₀",
    "MolarMass": 128.26,
    "C": 9,
    "H": 20,
    "O": 0,
    "N": 0,
    "S": 0,
    "AshContent": 0,
    "MoistureContent": 0,
    "HeatingValue": 42.00,
    "HHV": 46.80
  },
  {
    "Name": "Decane",
    "Type": "Gas",
    "Formula": "C10H22",
    "Symbol": "C₁₀H₂₂",
    "MolarMass": 142.29,
    "C": 10,
    "H": 22,
    "O": 0,
    "N": 0,
    "S": 0,
    "AshContent": 0,
    "MoistureContent": 0,
    "HeatingValue": 41.25,
    "HHV": 46.20
  },
  {
    "Name": "Butene",
    "Type": "Gas",
    "Formula": "C4H8",
    "Symbol": "C₄H₈",
    "MolarMass": 56.11,
    "C": 4,
    "H": 8,
    "O": 0,
    "N": 0,
    "S": 0,
    "AshContent": 0,
    "MoistureContent": 0,
    "HeatingValue": 44.75,
    "HHV": 48.50
  },
  {
    "Name": "Propylene",
    "Type": "Gas",
    "Formula": "C3H6",
    "Symbol": "C₃H₆",
    "MolarMass": 42.08,
    "C": 3,
    "H": 6,
    "O": 0,
    "N": 0,
    "S": 0,
    "AshContent": 0,
    "MoistureContent": 0,
    "HeatingValue": 45.80,
    "HHV": 49.80
  },
  {
    "Name": "n-Pentene",
    "Type": "Liquid",
    "Formula": "C5H10",
    "Symbol": "C₅H₁₀",
    "MolarMass": 70.13,
    "C": 5,
    "H": 10,
    "O": 0,
    "N": 0,
    "S": 0,
    "AshContent": 0,
    "MoistureContent": 0,
    "HeatingValue": 44.40,
    "HHV": 47.80
  },
  {
    "Name": "Acetylene",
    "Type": "Gas",
    "Formula": "C2H2",
    "Symbol": "C₂H₂",
    "MolarMass": 26.04,
    "C": 2,
    "H": 2,
    "O": 0,
    "N": 0,
    "S": 0,
    "AshContent": 0,
    "MoistureContent": 0,
    "HeatingValue": 48.70,
    "HHV": 54.80
  },
  {
    "Name": "Benzene",
    "Type": "Liquid",
    "Formula": "C6H6",
    "Symbol": "C₆H₆",
    "MolarMass": 78.11,
    "C": 6,
    "H": 6,
    "O": 0,
    "N": 0,
    "S": 0,
    "AshContent": 0.1,
    "MoistureContent": 0,
    "HeatingValue": 40.60,
    "HHV": 43.90
  },
  {
    "Name": "Toluene",
    "Type": "Liquid",
    "Formula": "C7H8",
    "Symbol": "C₇H₈",
    "MolarMass": 92.14,
    "C": 7,
    "H": 8,
    "O": 0,
    "N": 0,
    "S": 0,
    "AshContent": 0.1,
    "MoistureContent": 0,
    "HeatingValue": 40.50,
    "HHV": 43.60
  },
  {
    "Name": "Xylene",
    "Type": "Liquid",
    "Formula": "C8H10",
    "Symbol": "C₈H₁₀",
    "MolarMass": 106.17,
    "C": 8,
    "H": 10,
    "O": 0,
    "N": 0,
    "S": 0,
    "AshContent": 0.1,
    "MoistureContent": 0,
    "HeatingValue": 40.60,
    "HHV": 43.60
  },
  {
    "Name": "Naphthalene",
    "Type": "Solid",
    "Formula": "C10H8",
    "Symbol": "C₁₀H₈",
    "MolarMass": 128.17,
    "C": 10,
    "H": 8,
    "O": 0,
    "N": 0,
    "S": 0,
    "AshContent": 0.2,
    "MoistureContent": 0,
    "HeatingValue": 40.10,
    "HHV": 43.00
  },
  {
    "Name": "Propyne",
    "Type": "Gas",
    "Formula": "C3H4",
    "Symbol": "C₃H₄",
    "MolarMass": 40.06,
    "C": 3,
    "H": 4,
    "O": 0,
    "N": 0,
    "S": 0,
    "AshContent": 0,
    "MoistureContent": 0,
    "HeatingValue": 48.20,
    "HHV": 53.50
  },
  {
    "Name": "Butyne",
    "Type": "Gas",
    "Formula": "C4H6",
    "Symbol": "C₄H₆",
    "MolarMass": 54.09,
    "C": 4,
    "H": 6,
    "O": 0,
    "N": 0,
    "S": 0,
    "AshContent": 0,
    "MoistureContent": 0,
    "HeatingValue": 46.50,
    "HHV": 51.60
  },
  {
    "Name": "Methyl Alcohol",
    "Type": "Liquid",
    "Formula": "CH3OH",
    "Symbol": "CH₃OH",
    "MolarMass": 32.04,
    "C": 1,
    "H": 4,
    "O": 1,
    "N": 0,
    "S": 0,
    "AshContent": 0,
    "MoistureContent": 0,
    "HeatingValue": 19.90,
    "HHV": 22.70
  },
  {
    "Name": "Ethyl Alcohol",
    "Type": "Liquid",
    "Formula": "C2H5OH",
    "Symbol": "C₂H₅OH",
    "MolarMass": 46.07,
    "C": 2,
    "H": 6,
    "O": 1,
    "N": 0,
    "S": 0,
    "AshContent": 0,
    "MoistureContent": 0,
    "HeatingValue": 26.80,
    "HHV": 29.70
  },
  {
    "Name": "Carbon Monoxide",
    "Type": "Gas",
    "Formula": "CO",
    "Symbol": "CO",
    "MolarMass": 28.01,
    "C": 1,
    "H": 0,
    "O": 1,
    "N": 0,
    "S": 0,
    "AshContent": 0,
    "MoistureContent": 0,
    "HeatingValue": 10.11,
    "HHV": 10.11
  },
  {
    "Name": "Hydrogen",
    "Type": "Gas",
    "Formula": "H2",
    "Symbol": "H₂",
    "MolarMass": 2.02,
    "C": 0,
    "H": 2,
    "O": 0,
    "N": 0,
    "S": 0,
    "AshContent": 0,
    "MoistureContent": 0,
    "HeatingValue": 120.00,
    "HHV": 141.80
  },
  {
    "Name": "Hydrogen Sulfide",
    "Type": "Gas",
    "Formula": "H2S",
    "Symbol": "H₂S",
    "MolarMass": 34.08,
    "C": 0,
    "H": 2,
    "O": 0,
    "N": 0,
    "S": 1,
    "AshContent": 0,
    "MoistureContent": 0,
    "HeatingValue": 17.90,
    "HHV": 18.60
  },
  {
    "Name": "Ammonia",
    "Type": "Gas",
    "Formula": "NH3",
    "Symbol": "NH₃",
    "MolarMass": 17.03,
    "C": 0,
    "H": 3,
    "O": 0,
    "N": 1,
    "S": 0,
    "AshContent": 0,
    "MoistureContent": 0,
    "HeatingValue": 18.60,
    "HHV": 22.50
  },
  {
    "Name": "Carbon Dioxide",
    "Type": "Gas",
    "Formula": "CO2",
    "Symbol": "CO₂",
    "MolarMass": 44.01,
    "C": 1,
    "H": 0,
    "O": 2,
    "N": 0,
    "S": 0,
    "AshContent": 0,
    "MoistureContent": 0,
    "HeatingValue": 0.00,
    "HHV": 0.00
  },
  {
    "Name": "Sulfur Dioxide",
    "Type": "Gas",
    "Formula": "SO2",
    "Symbol": "SO₂",
    "MolarMass": 64.06,
    "C": 0,
    "H": 0,
    "O": 2,
    "N": 0,
    "S": 1,
    "AshContent": 0,
    "MoistureContent": 0,
    "HeatingValue": 0.00,
    "HHV": 0.00
  },
  {
    "Name": "Water",
    "Type": "Liquid",
    "Formula": "H2O",
    "Symbol": "H₂O",
    "MolarMass": 18.02,
    "C": 0,
    "H": 2,
    "O": 1,
    "N": 0,
    "S": 0,
    "AshContent": 0,
    "MoistureContent": 100,
    "HeatingValue": 0.00,
    "HHV": 0.00
  },
  {
    "Name": "Nitrogen",
    "Type": "Gas",
    "Formula": "N2",
    "Symbol": "N₂",
    "MolarMass": 28.02,
    "C": 0,
    "H": 0,
    "O": 0,
    "N": 2,
    "S": 0,
    "AshContent": 0,
    "MoistureContent": 0,
    "HeatingValue": 0.00,
    "HHV": 0.00
  },
  {
    "Name": "Oxygen",
    "Type": "Gas",
    "Formula": "O2",
    "Symbol": "O₂",
    "MolarMass": 32.00,
    "C": 0,
    "H": 0,
    "O": 2,
    "N": 0,
    "S": 0,
    "AshContent": 0,
    "MoistureContent": 0,
    "HeatingValue": 0.00,
    "HHV": 0.00
  },
  {
    "Name": "Anthracite Coal",
    "Type": "Solid",
    "Formula": "C",
    "Symbol": "C",
    "MolarMass": 12.01,
    "C": 0.95,
    "H": 0.03,
    "O": 0.01,
    "N": 0.005,
    "S": 0.005,
    "AshContent": 10,
    "MoistureContent": 5,
    "HeatingValue": 30.00,
    "HHV": 32.00
  },
  {
    "Name": "Bituminous Coal",
    "Type": "Solid",
    "Formula": "C",
    "Symbol": "C",
    "MolarMass": 12.01,
    "C": 0.85,
    "H": 0.05,
    "O": 0.06,
    "N": 0.015,
    "S": 0.025,
    "AshContent": 12,
    "MoistureContent": 8,
    "HeatingValue": 27.00,
    "HHV": 29.00
  },
  {
    "Name": "Sub-Bituminous Coal",
    "Type": "Solid",
    "Formula": "C",
    "Symbol": "C",
    "MolarMass": 12.01,
    "C": 0.75,
    "H": 0.05,
    "O": 0.15,
    "N": 0.01,
    "S": 0.01,
    "AshContent": 15,
    "MoistureContent": 15,
    "HeatingValue": 25.00,
    "HHV": 26.00
  },
  {
    "Name": "Lignite",
    "Type": "Solid",
    "Formula": "C",
    "Symbol": "C",
    "MolarMass": 12.01,
    "C": 0.65,
    "H": 0.04,
    "O": 0.25,
    "N": 0.01,
    "S": 0.01,
    "AshContent": 20,
    "MoistureContent": 25,
    "HeatingValue": 18.00,
    "HHV": 20.00
  },
  {
    "Name": "Wood (Dry)",
    "Type": "Solid",
    "Formula": "C6H10O5",
    "Symbol": "C₆H₁₀O₅",
    "MolarMass": 162.14,
    "C": 6,
    "H": 10,
    "O": 5,
    "N": 0,
    "S": 0,
    "AshContent": 1,
    "MoistureContent": 10,
    "HeatingValue": 16.50,
    "HHV": 18.50
  },
  {
    "Name": "Bagasse",
    "Type": "Solid",
    "Formula": "C6H10O5",
    "Symbol": "C₆H₁₀O₅",
    "MolarMass": 162.14,
    "C": 6,
    "H": 10,
    "O": 5,
    "N": 0,
    "S": 0,
    "AshContent": 2,
    "MoistureContent": 50,
    "HeatingValue": 7.50,
    "HHV": 9.00
  },
  {
    "Name": "Peat",
    "Type": "Solid",
    "Formula": "C",
    "Symbol": "C",
    "MolarMass": 12.01,
    "C": 0.60,
    "H": 0.05,
    "O": 0.30,
    "N": 0.015,
    "S": 0.005,
    "AshContent": 10,
    "MoistureContent": 40,
    "HeatingValue": 15.00,
    "HHV": 17.00
  },
  {
    "Name": "Rice Husk",
    "Type": "Solid",
    "Formula": "C6H10O5",
    "Symbol": "C₆H₁₀O₅",
    "MolarMass": 162.14,
    "C": 6,
    "H": 10,
    "O": 5,
    "N": 0,
    "S": 0,
    "AshContent": 15,
    "MoistureContent": 10,
    "HeatingValue": 13.50,
    "HHV": 15.50
  },
  {
    "Name": "Sawdust",
    "Type": "Solid",
    "Formula": "C6H10O5",
    "Symbol": "C₆H₁₀O₅",
    "MolarMass": 162.14,
    "C": 6,
    "H": 10,
    "O": 5,
    "N": 0,
    "S": 0,
    "AshContent": 1,
    "MoistureContent": 20,
    "HeatingValue": 15.00,
    "HHV": 17.00
  },
  {
    "Name": "Municipal Solid Waste",
    "Type": "Solid",
    "Formula": "Varies",
    "Symbol": "MSW",
    "MolarMass": null,
    "C": 0.50,
    "H": 0.06,
    "O": 0.35,
    "N": 0.03,
    "S": 0.01,
    "AshContent": 25,
    "MoistureContent": 30,
    "HeatingValue": 10.00,
    "HHV": 12.00
  },
  {
    "Name": "Biodiesel",
    "Type": "Liquid",
    "Formula": "C16H30O2",
    "Symbol": "C₁₆H₃₀O₂",
    "MolarMass": 254.41,
    "C": 16,
    "H": 30,
    "O": 2,
    "N": 0,
    "S": 0,
    "AshContent": 0,
    "MoistureContent": 0,
    "HeatingValue": 37.80,
    "HHV": 39.80
  },
  {
    "Name": "Bioethanol",
    "Type": "Liquid",
    "Formula": "C2H5OH",
    "Symbol": "C₂H₅OH",
    "MolarMass": 46.07,
    "C": 2,
    "H": 6,
    "O": 1,
    "N": 0,
    "S": 0,
    "AshContent": 0,
    "MoistureContent": 5,
    "HeatingValue": 26.70,
    "HHV": 29.70
  },
  {
    "Name": "Biogas",
    "Type": "Gas",
    "Formula": "Varies",
    "Symbol": "Biogas",
    "MolarMass": 28.00,
    "C": 1,
    "H": 4,
    "O": 0,
    "N": 0,
    "S": 0,
    "AshContent": 0,
    "MoistureContent": 10,
    "HeatingValue": 20.00,
    "HHV": 22.00
  },
  {
    "Name": "Syngas",
    "Type": "Gas",
    "Formula": "Varies",
    "Symbol": "Syngas",
    "MolarMass": 28.00,
    "C": 1,
    "H": 2,
    "O": 1,
    "N": 0,
    "S": 0,
    "AshContent": 0,
    "MoistureContent": 0,
    "HeatingValue": 10.00,
    "HHV": 12.00
  }
]
